serpex_sdk/__init__.py
serpex_sdk/client.py
serpex_sdk/exceptions.py
serpex_sdk/types.py
serpex_sdk-1.0.4.dist-info/licenses/LICENSE
serpex_sdk-1.0.4.dist-info/METADATA
serpex_sdk-1.0.4.dist-info/WHEEL
serpex_sdk-1.0.4.dist-info/top_level.txt
serpex_sdk-1.0.4.dist-info/RECORD
