Metadata-Version: 2.4
Name: serpex-sdk
Version: 1.0.4
Summary: Official Python SDK for Serpex SERP API - Fetch search results in JSON format
Home-page: https://github.com/divyeshradadiya/serp-frontend
Author: Serpex Team
Author-email: Serpex Team <support@serpex.dev>
License: MIT
Project-URL: Homepage, https://github.com/divyeshradadiya/serp-frontend
Project-URL: Repository, https://github.com/divyeshradadiya/serp-frontend
Project-URL: Bug Reports, https://github.com/divyeshradadiya/serp-frontend/issues
Project-URL: Documentation, https://github.com/divyeshradadiya/serp-frontend#readme
Keywords: serp,search,api,google,search-results,seo,python,sdk
Classifier: Development Status :: 5 - Production/Stable
Classifier: Intended Audience :: Developers
Classifier: License :: OSI Approved :: MIT License
Classifier: Operating System :: OS Independent
Classifier: Programming Language :: Python :: 3
Classifier: Programming Language :: Python :: 3.8
Classifier: Programming Language :: Python :: 3.9
Classifier: Programming Language :: Python :: 3.10
Classifier: Programming Language :: Python :: 3.11
Classifier: Programming Language :: Python :: 3.12
Classifier: Topic :: Internet :: WWW/HTTP :: Dynamic Content
Classifier: Topic :: Software Development :: Libraries :: Python Modules
Requires-Python: >=3.8
License-File: LICENSE
Requires-Dist: requests>=2.25.0
Requires-Dist: typing-extensions>=4.0.0; python_version < "3.10"
Dynamic: author
Dynamic: home-page
Dynamic: license-file
Dynamic: requires-python
